slim_eval/__init__.py
slim_eval/analysis.py
slim_eval/cli.py
slim_eval/evaluator.py
slim_eval/quantization.py
slim_eval/utils.py
slim_eval/benchmarks/__init__.py
slim_eval/benchmarks/accuracy.py
slim_eval/benchmarks/base.py
slim_eval/benchmarks/energy.py
slim_eval/benchmarks/performance.py
slim_eval-0.1.3.dist-info/licenses/LICENSE
slim_eval-0.1.3.dist-info/METADATA
slim_eval-0.1.3.dist-info/WHEEL
slim_eval-0.1.3.dist-info/entry_points.txt
slim_eval-0.1.3.dist-info/top_level.txt
slim_eval-0.1.3.dist-info/RECORD
