Metadata-Version: 2.4
Name: slim-eval
Version: 0.1.3
Summary: Complete Small Language Model Evaluation Framework - Tracking Latency, Memory, Energy, and Accuracy
Requires-Python: >=3.10
License-File: LICENSE
Requires-Dist: pandas==2.3.3
Requires-Dist: numpy==2.2.6
Requires-Dist: matplotlib==3.10.7
Requires-Dist: seaborn==0.13.2
Requires-Dist: typer==0.20.0
Provides-Extra: all
Requires-Dist: torch==2.8.0; extra == "all"
Requires-Dist: torchvision==0.23.0; extra == "all"
Requires-Dist: torchaudio==2.8.0; extra == "all"
Requires-Dist: vllm==0.11.0; extra == "all"
Requires-Dist: llmcompressor==0.7.1; extra == "all"
Requires-Dist: transformers==4.55.2; extra == "all"
Requires-Dist: accelerate==1.10.0; extra == "all"
Requires-Dist: tokenizers==0.21.4; extra == "all"
Requires-Dist: lm-eval==0.4.9.2; extra == "all"
Requires-Dist: nvidia-ml-py==12.575.51; extra == "all"
Requires-Dist: pynvml==12.0.0; extra == "all"
Requires-Dist: tqdm==4.67.1; extra == "all"
Requires-Dist: psutil==7.1.3; extra == "all"
Requires-Dist: wandb==0.18.5; extra == "all"
Provides-Extra: dev
Requires-Dist: jupyter==1.0.0; extra == "dev"
Requires-Dist: ipykernel==6.25.0; extra == "dev"
Requires-Dist: ipywidgets==8.1.0; extra == "dev"
Dynamic: license-file
